README.txt
setup.cfg
setup.py
docs/HISTORY.txt
pcommerce/__init__.py
pcommerce.stock.egg-info/PKG-INFO
pcommerce.stock.egg-info/SOURCES.txt
pcommerce.stock.egg-info/dependency_links.txt
pcommerce.stock.egg-info/entry_points.txt
pcommerce.stock.egg-info/namespace_packages.txt
pcommerce.stock.egg-info/not-zip-safe
pcommerce.stock.egg-info/requires.txt
pcommerce.stock.egg-info/top_level.txt
pcommerce/stock/__init__.py
pcommerce/stock/configure.zcml
pcommerce/stock/extender.py
pcommerce/stock/interfaces.py
pcommerce/stock/setuphandlers.py
pcommerce/stock/stock.py
pcommerce/stock/utils.py
pcommerce/stock/Extensions/Install.py
pcommerce/stock/Extensions/__init__.py
pcommerce/stock/browser/__init__.py
pcommerce/stock/browser/cart.pt
pcommerce/stock/browser/cart.py
pcommerce/stock/browser/checkout.py
pcommerce/stock/browser/configure.zcml
pcommerce/stock/browser/stock.pt
pcommerce/stock/browser/stock.py
pcommerce/stock/i18n/pcommerce-de.mo
pcommerce/stock/i18n/pcommerce-de.po
pcommerce/stock/i18n/pcommerce-nl.po
pcommerce/stock/i18n/pcommerce-plone-de.mo
pcommerce/stock/i18n/pcommerce-plone-de.po
pcommerce/stock/i18n/pcommerce-plone-nl.po
pcommerce/stock/i18n/pcommerce-plone.pot
pcommerce/stock/i18n/pcommerce.pot
pcommerce/stock/profiles/default/browserlayer.xml
pcommerce/stock/profiles/default/metadata.xml
pcommerce/stock/profiles/default/pcommerce.stock_install.txt
pcommerce/stock/profiles/default/types.xml
pcommerce/stock/profiles/default/types/Product.xml
pcommerce/stock/profiles/uninstall/pcommerce.stock_uninstall.txt