Metadata-Version: 1.0
Name: pcommerce.stock
Version: 1.0a4
Summary: Provides stock functionality for PCommerce
Home-page: http://raptus.com
Author: Raptus AG
Author-email: dev@raptus.com
License: GPL
Platform: UNKNOWN
Classifier: Programming Language :: Python
Classifier: Topic :: Software Development :: Libraries :: Python Modules
